ssb_befolkning_fagfunksjoner/__init__.py
ssb_befolkning_fagfunksjoner/__main__.py
ssb_befolkning_fagfunksjoner/bef_variables/__init__.py
ssb_befolkning_fagfunksjoner/bef_variables/population.py
ssb_befolkning_fagfunksjoner/date_utils/__init__.py
ssb_befolkning_fagfunksjoner/date_utils/dates.py
ssb_befolkning_fagfunksjoner/date_utils/event_params.py
ssb_befolkning_fagfunksjoner/demographics/__init__.py
ssb_befolkning_fagfunksjoner/demographics/birth_rates.py
ssb_befolkning_fagfunksjoner/demographics/dublettsjekk.py
ssb_befolkning_fagfunksjoner/demographics/sml_rader.py
ssb_befolkning_fagfunksjoner/klass_utils/__init__.py
ssb_befolkning_fagfunksjoner/klass_utils/change_mapping.py
ssb_befolkning_fagfunksjoner/klass_utils/komm_nr.py
ssb_befolkning_fagfunksjoner/klass_utils/level_mapping.py
ssb_befolkning_fagfunksjoner/klass_utils/mappers.py
ssb_befolkning_fagfunksjoner/py.typed
ssb_befolkning_fagfunksjoner-0.1.3.dist-info/METADATA
ssb_befolkning_fagfunksjoner-0.1.3.dist-info/WHEEL
ssb_befolkning_fagfunksjoner-0.1.3.dist-info/entry_points.txt
ssb_befolkning_fagfunksjoner-0.1.3.dist-info/licenses/LICENSE
ssb_befolkning_fagfunksjoner-0.1.3.dist-info/RECORD
