Metadata-Version: 2.4
Name: ssb-befolkning-fagfunksjoner
Version: 0.1.3
Summary: Befolkning Fagfunksjoner
License-Expression: MIT
License-File: LICENSE
Author: Stian Nergård
Author-email: grd@ssb.no
Requires-Python: >=3.11,<4.0
Classifier: Development Status :: 4 - Beta
Classifier: Programming Language :: Python :: 3
Classifier: Programming Language :: Python :: 3.11
Classifier: Programming Language :: Python :: 3.12
Classifier: Programming Language :: Python :: 3.13
Classifier: Programming Language :: Python :: 3.14
Requires-Dist: click (>=8.0.1)
Requires-Dist: ipykernel (>=6.29.5,<7.0.0)
Requires-Dist: networkx (<3.5)
Requires-Dist: pandas (>=2.2.3,<3.0.0)
Requires-Dist: python-dateutil (>=2.9.0.post0,<3.0.0)
Requires-Dist: ssb-klass-python (>=1.0.2,<2.0.0)
Requires-Dist: tabulate (>=0.9.0,<0.10.0)
Requires-Dist: types-networkx (>=3.5.0.20251001,<4.0.0.0)
Requires-Dist: types-python-dateutil (>=2.9.0.20250822,<3.0.0.0)
Requires-Dist: universal-pathlib (>=0.2.6,<0.3.0)
Project-URL: Changelog, https://github.com/statisticsnorway/ssb-befolkning-fagfunksjoner/releases
Project-URL: Documentation, https://statisticsnorway.github.io/ssb-befolkning-fagfunksjoner
Project-URL: Homepage, https://github.com/statisticsnorway/ssb-befolkning-fagfunksjoner
Project-URL: Repository, https://github.com/statisticsnorway/ssb-befolkning-fagfunksjoner
